esistatus/__init__.py
esistatus/app_settings.py
esistatus/apps.py
esistatus/auth_hooks.py
esistatus/constants.py
esistatus/models.py
esistatus/providers.py
esistatus/tasks.py
esistatus/urls.py
esistatus/views.py
esistatus/handler/cache.py
esistatus/locale/.gitkeep
esistatus/locale/django.pot
esistatus/locale/cs_CZ/LC_MESSAGES/django.mo
esistatus/locale/cs_CZ/LC_MESSAGES/django.po
esistatus/locale/de/LC_MESSAGES/django.mo
esistatus/locale/de/LC_MESSAGES/django.po
esistatus/locale/es/LC_MESSAGES/django.mo
esistatus/locale/es/LC_MESSAGES/django.po
esistatus/locale/fr_FR/LC_MESSAGES/django.mo
esistatus/locale/fr_FR/LC_MESSAGES/django.po
esistatus/locale/it_IT/LC_MESSAGES/django.mo
esistatus/locale/it_IT/LC_MESSAGES/django.po
esistatus/locale/ja/LC_MESSAGES/django.mo
esistatus/locale/ja/LC_MESSAGES/django.po
esistatus/locale/ko_KR/LC_MESSAGES/django.mo
esistatus/locale/ko_KR/LC_MESSAGES/django.po
esistatus/locale/nl_NL/LC_MESSAGES/django.mo
esistatus/locale/nl_NL/LC_MESSAGES/django.po
esistatus/locale/pl_PL/LC_MESSAGES/django.mo
esistatus/locale/pl_PL/LC_MESSAGES/django.po
esistatus/locale/ru/LC_MESSAGES/django.mo
esistatus/locale/ru/LC_MESSAGES/django.po
esistatus/locale/sk/LC_MESSAGES/django.mo
esistatus/locale/sk/LC_MESSAGES/django.po
esistatus/locale/uk/LC_MESSAGES/django.mo
esistatus/locale/uk/LC_MESSAGES/django.po
esistatus/locale/zh_Hans/LC_MESSAGES/django.mo
esistatus/locale/zh_Hans/LC_MESSAGES/django.po
esistatus/migrations/0001_initial.py
esistatus/migrations/0002_openapi_status.py
esistatus/migrations/__init__.py
esistatus/static/esistatus/css/esistatus.css
esistatus/static/esistatus/css/esistatus.min.css
esistatus/static/esistatus/css/esistatus.min.css.map
esistatus/static/esistatus/javascript/esistatus-dashboard-widget.js
esistatus/static/esistatus/javascript/esistatus-dashboard-widget.min.js
esistatus/static/esistatus/javascript/esistatus-dashboard-widget.min.js.map
esistatus/static/esistatus/javascript/esistatus.js
aa_esi_status-3.3.1.dist-info/METADATA
aa_esi_status-3.3.1.dist-info/WHEEL
aa_esi_status-3.3.1.dist-info/licenses/LICENSE
aa_esi_status-3.3.1.dist-info/RECORD
